Workbook
Name BRANCHOFSERVICE: Data_Income!$C$813:$C$828
Name FAMILYSIZE: #REF!
Name FREQUENCY: Data_Income!$C$48:$C$57
Name M_DOCTYPES: Data_Income!$C$106:$C$115
Name M_PAYDOCS: Data_Income!$B$48:$B$57
Name M_YEARS: Data_Income!$C$27:$C$32
Name RESIDUALACTUAL: 'Res Inc Data'!$B$46
Name RESIDUALDIFF: 'Res Inc Data'!$B$48
Name RESIDUALREQUIRED: 'Res Inc Data'!$B$45
Name STATESELECTED: 'Res Inc Data'!$B$41
Name STATESLIST: 'Res Inc Data'!$D$67:$D$118
Name WVOEHEADINGS: Data_Income!$C$94:$C$102
Name YEARN: Data_Income!$B$8
Name YEARP1: Data_Income!$B$10
Name YEARP2: Data_Income!$B$11
Name YRCB: Data_Income!$B$13
Name YRP1B: Data_Income!$B$14
Name YRP1E: Data_Income!$B$15
Name YRP2B: Data_Income!$B$16
Name YRP2E: Data_Income!$B$17

Sheet 个人rental income(4个以下)
B1: Rental Income Worksheet
B2: Principal Residence, 2- to 4-unit Property: Monthly Qualifying Rental Income
B3: Documentation Required: | F3: Address of Principal Residence:
B4: § Schedule E (IRS Form 1040) OR
B5: § Lease Agreement or Fannie Mae Form 1007 or Form 1025 | E5: Enter | F5: Rental Unit | G5: Rental Unit | H5: Rental Unit
B7: Step 1. When using Schedule E, determine the number of months the property was in service by dividing the Fair Rental Days by 30.
B8: If Fair Rental Days are not reported, the property is considered to be in service for 12 months unless there is evidence of a shorter term of service.
B9: Step 1. Result: The number of months the property was in service: | E9: Result
B10: Step 2. Calculate monthly qualifying rental income using Step 2A: Schedule E OR Step 2B: Lease Agreement or Fannie Mae Form 1025.
B11: Step 2 A. Schedule E - Part I For each property complete ONLY 2A or 2B
B12: A1 | C12: Enter total rents received (from the non-owner-occupied units). May enter rent from individual unit(s) or combine. | E12: Enter
B13: A2 | C13: Subtract total expenses. | E13: Subtract
B14: A3 | C14: Add back insurance expense. | E14: Add
B15: A4 | C15: Add back mortgage interest paid. | E15: Add
B16: A5 | C16: Add back tax expense. | E16: Add
B17: A6 | C17: Add back homeowners’ association dues. This expense must be specifically identified on Schedule E in order to add it back. | E17: Add
B18: A7 | C18: Add back depreciation expense or depletion. | E18: Add
B19: A8 | C19: Add back any one-time extraordinary expense (e.g., casualty loss). There must be evidence of the nature of the one-time extraordinary expense. | E19: Add
C20: Equals adjusted rental income. | E20: Total | F20: =SUM(F12,F14:F19)-F13 -> 0 | G20: =SUM(G12,G14:G19)-G13 -> 0 | H20: =SUM(H12,H14:H19)-H13 -> 0
B21: A9 | C21: Divide by the number of months the property was in service (Step 1 Result). | E21: Divide | F21: =F9 -> 0 | G21: =G9 -> 0 | H21: =H9 -> 0
B22: Step 2A. Result: Monthly qualifying rental income (or loss): | E22: Result | F22: =IF(F21=0,0,F20/F21) -> 0 | G22: =IF(G21=0,0,G20/G21) -> 0 | H22: =IF(H21=0,0,H20/H21) -> 0
B23: Step 2B. Lease Agreement OR Fannie Mae Form 1025 For each property complete ONLY 2A or 2B
B24: This method is used when the transaction is a purchase, the property was acquired subsequent to the most recent tax filing.
B25: B1 | C25: Enter the gross monthly rent (from the lease agreement) or market rent (from Form 1025) for the applicable rental unit | E25: Enter
B28: B2 | C28: Multiply gross monthly rent or market rent by 75% (.75). The remaining 25% accounts for vacancy loss, maintenance, and management expenses. | E28: Multiply | F28: x.75 | G28: x.75 | H28: x.75
C29: Equals monthly rental income per unit | E29: Total | F29: =F25*0.75 -> 0 | G29: =G25*0.75 -> 0 | H29: =H25*0.75 -> 0
B30: B3 | C30: Combine the monthly rental income of all non-owner-occupied rental units (up to a maximum of 3 rental units since rental income is not eligible on the unit occupied by the borrower). | E30: Add | F30: =F22+G22+H22 -> 0
B31: Step 2B. Result: Monthly qualifying rental income: | E31: Result | F31: =F29+G29+H29 -> 0
B32: Step 3. Determine the qualifying impact using the combined result of Step 2A or Step 2B.
B33: 3A | C33: Add the monthly qualifying rental income to the borrower’s monthly qualifying income. | F33: =F22+G22+H22+F31 -> 0
B34: 3B | C34: Identify the full amount of the PITIA as the borrower’s primary housing expense and include it in the debt-to-income ratio. Use proposed PITIA when the subject property; existing PITIA when not the subject property.
B35: DU Data Entry | D35: Monthly Income and Combined Housing Expenses | F35: Mortgage Liabilities
B36: Subject Property | D36: Enter the amount of the monthly qualifying income “Subject Net Cash.” | F36: Include as the borrower’s primary housing expense. For refinance transactions, identify the mortgage as a subject property lien.
B37: Non-Subject Property | D37: Enter the amount of the monthly qualifying income “Net Rental.” | F37: Include as the borrower’s primary housing expense.
B38: Refer to the Rental Income topic in the Selling Guide for additional guidance.

Sheet Back-to-Work
B3: Income Calculations Worksheet
B4: FHA Back to Work Initiative
C7: Borrower: | O7: =IF(#REF!="","",#REF!) -> #REF! | BR7: Loan #: | CE7: =IF(#REF!="","",#REF!) -> #REF!
C10: TOTAL HOUSEHOLD EARNINGS AT TIME OF ECONOMIC EVENT
C11: Actual Date of Economic Event
C12: Borrower's total monthly income at time of economic event | CK12: 0
C13: Other household monthly income at time of economic event | CK13: 0
C14: Total Household Monthly Income at time of economic event | CK14: =SUM(CK12:DA13) -> 0
C17: PERIOD AFTER ECONOMIC EVENT (MINIMUM 6 MONTHS)
C18: Date for the six month period after the date of Economic Event | CK18: =IF(CK11="","",EDATE(CK11,6))
C19: =Data_Income!B948 -> Borrower's total income beginning on 1/1/1900 and ending on 7/1/1900 | CK19: 0
C20: =Data_Income!B949 -> Other household total income beginning on 1/1/1900 and ending on 7/1/1900 | CK20: 0
C21: =Data_Income!B950 -> Grand Total Household Income beginning on 1/1/1900 and ending on 7/1/1900 | CK21: =SUM(CK19:DA20) -> 0
C23: =Data_Income!B951 -> Grand Total Household Monthly Income Average for the period of 1/1/1900 to 7/1/1900 | CK23: =Data_Income!E946 -> 0
C25: Increase / Decrease difference in monthly earnings | CK25: =Data_Income!F946
C28: =Data_Income!B953
C29: =Data_Income!B954
C31: Required Documentation
C32: Loss of Employment
C33: ● | D33: Verify with written VOE to show termination date.
C34: ● | D34: If employer went out of business, then document with copy of borrowers' severance package letter, other publicly available document that the
D35: employer went out of business, and/or receipt of Unemployment income within timeframe.
C36: Loss of Income
C37: ● | D37: Must verify and ensure proper documentation is provided to reflect what the borrower's household income was prior to the Economic Event.
C38: ● | D38: Must verify that either the loss of employment, the loss of income or the loss of both trigerred the Economic Event by documenting the
D39: borrower's household income was after the Economic Event was trigerred.
C40: Satisfactory Credit BEFORE Economic Event
C41: ● | D41: Must verify that borrower(s) had a satisfactory credit history 12 months (minimum) before the Economic Event.
C42: Satisfactory Credit AFTER Economic Event
C43: ● | D43: Must verify no late payments in the last 12 months since the Economic Event.
C44: ● | D44: Borrower's credit history is clear of late housing or installment debt payments and major derogatory credit issues on revolving debts.
C45: ● | D45: Any open mortgage is current and shows a 12 month history of satisfactory payments. Mortgage payments brought current through a loan
D46: modification is acceptable so long as all payments are documented as being paid on time as per the loan modification agreement.
C47: Collections
C48: Regardless of the initial AUS findings, if the total outstanding balance of ALL collections for ALL borrowers is > $2,000, the collections to be paid
C49: off at closing, or provide verification with a letter from the creditor on their letterhead or a credit supplement that borrower has been in a
C50: satisfactory payment plan. Must qualify the borrower with the verified payment amount. If no payment can be verified, qualify the borrower with
C51: each collection account using 5% of the balance as the payment.
C52: Note: Medical collections and charge-offs are excluded from this policy. This policy includes the collection accounts for non-borrowing spouses
C53: who live in a community property state. Collection accounts may NOT be paid down to less than $2,000.
C54: Judgements
C55: Regardless of the initial AUS findings, Judgment(s) must be paid in full through closing of the transaction, or evidence judgment has been
C56: satisfactorily paid prior to close, or evidence borrowers are in a payment plan with the following requirements: Provide a copy of the agreement,
C57: payment must have been made in a timely manner, and evidence a minimum of 3 months scheduled payments have been made prior to close.
C58: Note: Borrowers may not pre-pay scheduled payments in advance to reflect 3 payments. This policy includes the judgments for non-borrowing
... C67: Housing Counseling
C68: ● | D68: Each participant must provide evidence that they have completed Homeownership Counseling (received a minimum of 1 hour one-on-one
D69: counseling), addressing the cause of the Economic Event and the actions taken to overcome the cause thereby reducing the likelihood of
D70: reoccurrence.
C71: ● | D71: Must be completed a minimum 30 days prior to loan application and no more than 6 months prior to submitting the loan to Lender. NO
D72: EXCEPTIONS!
C73: ● | D73: If there is a fee associated with the Housing Counseling requirement then, the Loan Estimate must reflect a Written Provider in box 6 in order to
D74: be compliant.
D77: This worksheet is not intended to be legal or comprehensive financial advice. The user assumes any legal liability and responsibility
D78: for the accuracy, completeness, usefulness, effectiveness, reliability, information and/or results obtained from the use of this worksheet.
D79: It is the responsibility of the user to be knowledgeable of the text and data contained in the worksheet, to ensure the accuracy of any
D80: documentation used to complete the worksheet, and that contents are in accordance with product, investor and regulatory requirements.

Sheet Data_Income
A1: BASIC PARAMETERS
A3: DATES
A5: Today Date | B5: =TODAY() -> 46099
A6: Today Month | B6: =MONTH(TODAY()) -> 3
A7: Today Day | B7: =DAY(B5) -> 18
A8: Year Today | B8: =YEAR(B5) -> 2026
A9: Year to Date | B9: =IF(#REF!="",YEAR(TODAY()),YEAR(#REF!)) -> #REF!
A10: Year Last | B10: =YEAR(TODAY())-1 -> 2025
A11: Year Previous | B11: =YEAR(TODAY())-2 -> 2024
A12: Doc Date | B12: =#REF! -> #REF!
A13: YR Today Beg | B13: =DATE(YEAR(B12),1,1) -> #REF! | C13: YRCB
A14: YR Last Beg | B14: =DATE((YEAR(TODAY())-1),1,1) -> 45658 | C14: YRP1B
A15: YR Last End | B15: =DATE((YEAR(TODAY())-1),12,31) -> 46022 | C15: YRP1E
A16: YR Prev Beg | B16: =DATE((YEAR(TODAY())-2),1,1) -> 45292 | C16: YRP2B
A17: YR Prev End | B17: =DATE((YEAR(TODAY())-2),12,31) -> 45657 | C17: YRP2E
A19: SS & MEDICARE WITHHOLDING CALCULATIONS PARAMETERS
A21: Earnings | B21: Tax % | C21: Withholdings
A22: 0 | B22: 0.062 | C22: =A22*B22 -> 0
B23: 0.0145 | C23: =A22*B23 -> 0
A25: YEAR SELECTIONS \ [ M_YEARS ] \ memory variable list begins with "Select Year" (B27) and ends with "2018" (B32)
A27: ↑ | C27: Select Year
A28: M_YEARS | C28: 2014
A29: | | C29: 2015
A30: | | C30: 2016
A31: | | C31: 2017
A32: ↓ | C32: 2018
A34: DEPRECIATION MILEAGE FACTORS
C36: Year | D36: FNMA Factor
A37: ↑ | C37: 2013 | D37: 0.23
A38: List of FNMA | C38: 2014 | D38: 0.22
A39: Depreciation | C39: 2015 | D39: 0.24
A40: Mileage | C40: 2016 | D40: 0.24
A41: Factors | C41: 2017 | D41: 0.24
A42: ↓ | C42: 2018 | D42: 0.24
A44: INCOME PAY PERIOD FREQUENCY \ [ M_PAYDOCS ] \ memory variable list begins with "Paystub" (C49) and ends with "Other" (C57)
D46: VLOOKUP
B47: Document | C47: Frequency | D47: Search | E47: Pay Periods | F47: Hours | G47: Term
A48: 1
A49: 2 | B49: Paystub | C49: Hourly (H) | D49: Annually (1) | E49: 1 | F49: 2080 | G49: annually
A50: 3 | B50: Written VOE | C50: Weekly (52) | D50: Bi-Weekly (26) | E50: 26 | F50: 80 | G50: bi-weekly
A51: 4 | B51: Paystub & VOE | C51: Bi-Weekly (26) | D51: Hourly (H) | E51: 2080 | F51: 1 | G51: hourly
A52: 5 | B52: Awards Letter | C52: Semi-Monthly (24) | D52: Monthly (12) | E52: 12 | F52: =2080/12 -> 173.33333 | G52: monthly
A53: 6 | B53: Bank Statement | C53: Monthly (12) | D53: Part-Time | E53: 0 | F53: 0 | G53: part-time
A54: 7 | B54: Multiple Docs | C54: Annually (1) | D54: Seasonal | E54: 0 | F54: 0 | G54: seasonal
A55: 8 | B55: IRS Form 1099 | C55: Part-Time | D55: Semi-Monthly (24) | E55: 24 | F55: =2080/24 -> 86.666667 | G55: semi-monthly
A56: 9 | B56: W2 | C56: Seasonal | D56: Varies | E56: 0 | F56: 0 | G56: varies
A57: 10 | B57: Other | C57: Varies / Averaged | D57: Weekly (52) | E57: 52 | F57: 40 | G57: weekly
A59: GOVERNMENT PAY PERIODS
B61: Pay Period Ending
B62: 2014 | C62: =B62+1 -> 2015 | D62: =C62+1 -> 2016 | E62: =D62+1 -> 2017 | F62: =E62+1 -> 2018 | G62: =F62+1 -> 2019 | H62: =G62+1 -> 2020
A63: 1 | B63: 2 | C63: 3 | D63: 4 | E63: 5 | F63: 6 | G63: 7 | H63: 8
A64: 1 | B64: 41636 | C64: =B89+14 -> 42000 | D64: =C89+14 -> 42364 | E64: =D89+14 -> 42728 | F64: =E89+14 -> 43092 | G64: =F89+14 -> 43456 | H64: =G89+14 -> 43820
A65: =A64+1 -> 2 | B65: =B64+14 -> 41650 | C65: =C64+14 -> 42014 | D65: =D64+14 -> 42378 | E65: =E64+14 -> 42742 | F65: =F64+14 -> 43106 | G65: =G64+14 -> 43470 | H65: =H64+14 -> 43834
A66: =A65+1 -> 3 | B66: =B65+14 -> 41664 | C66: =C65+14 -> 42028 | D66: =D65+14 -> 42392 | E66: =E65+14 -> 42756 | F66: =F65+14 -> 43120 | G66: =G65+14 -> 43484 | H66: =H65+14 -> 43848
A67: =A66+1 -> 4 | B67: =B66+14 -> 41678 | C67: =C66+14 -> 42042 | D67: =D66+14 -> 42406 | E67: =E66+14 -> 42770 | F67: =F66+14 -> 43134 | G67: =G66+14 -> 43498 | H67: =H66+14 -> 43862
A68: =A67+1 -> 5 | B68: =B67+14 -> 41692 | C68: =C67+14 -> 42056 | D68: =D67+14 -> 42420 | E68: =E67+14 -> 42784 | F68: =F67+14 -> 43148 | G68: =G67+14 -> 43512 | H68: =H67+14 -> 43876
A69: =A68+1 -> 6 | B69: =B68+14 -> 41706 | C69: =C68+14 -> 42070 | D69: =D68+14 -> 42434 | E69: =E68+14 -> 42798 | F69: =F68+14 -> 43162 | G69: =G68+14 -> 43526 | H69: =H68+14 -> 43890
A70: =A69+1 -> 7 | B70: =B69+14 -> 41720 | C70: =C69+14 -> 42084 | D70: =D69+14 -> 42448 | E70: =E69+14 -> 42812 | F70: =F69+14 -> 43176 | G70: =G69+14 -> 43540 | H70: =H69+14 -> 43904
A71: =A70+1 -> 8 | B71: =B70+14 -> 41734 | C71: =C70+14 -> 42098 | D71: =D70+14 -> 42462 | E71: =E70+14 -> 42826 | F71: =F70+14 -> 43190 | G71: =G70+14 -> 43554 | H71: =H70+14 -> 43918
A72: =A71+1 -> 9 | B72: =B71+14 -> 41748 | C72: =C71+14 -> 42112 | D72: =D71+14 -> 42476 | E72: =E71+14 -> 42840 | F72: =F71+14 -> 43204 | G72: =G71+14 -> 43568 | H72: =H71+14 -> 43932
A73: =A72+1 -> 10 | B73: =B72+14 -> 41762 | C73: =C72+14 -> 42126 | D73: =D72+14 -> 42490 | E73: =E72+14 -> 42854 | F73: =F72+14 -> 43218 | G73: =G72+14 -> 43582 | H73: =H72+14 -> 43946
A74: =A73+1 -> 11 | B74: =B73+14 -> 41776 | C74: =C73+14 -> 42140 | D74: =D73+14 -> 42504 | E74: =E73+14 -> 42868 | F74: =F73+14 -> 43232 | G74: =G73+14 -> 43596 | H74: =H73+14 -> 43960
A75: =A74+1 -> 12 | B75: =B74+14 -> 41790 | C75: =C74+14 -> 42154 | D75: =D74+14 -> 42518 | E75: =E74+14 -> 42882 | F75: =F74+14 -> 43246 | G75: =G74+14 -> 43610 | H75: =H74+14 -> 43974
A76: =A75+1 -> 13 | B76: =B75+14 -> 41804 | C76: =C75+14 -> 42168 | D76: =D75+14 -> 42532 | E76: =E75+14 -> 42896 | F76: =F75+14 -> 43260 | G76: =G75+14 -> 43624 | H76: =H75+14 -> 43988
... A89: =A88+1 -> 26 | B89: =B88+14 -> 41986 | C89: =C88+14 -> 42350 | D89: =D88+14 -> 42714 | E89: =E88+14 -> 43078 | F89: =F88+14 -> 43442 | G89: =G88+14 -> 43806 | H89: =H88+14 -> 44170
A92: PAY TYPES \ [ M_PAYTYPES ] \ memory variable list begins with "Click Here …" (C94) and continues until "Other" (C102)
A94: ↑ | C94: Click Here, then Click on Down Arrow (to the right) for a List of Additional Pay Types
A95: M_PAYTYPES | C95: BONUS | F95: \ Options for drop down selections
A96: | | C96: COMMISSIONS | F96: \ Options for drop down selections
A97: | | C97: DIFFERENTIAL | F97: \ Options for drop down selections
A98: | | C98: HOUSING ALLOWANCE | F98: \ Options for drop down selections
A99: | | C99: INCENTIVE | F99: \ Options for drop down selections
A100: | | C100: OVERTIME | F100: \ Options for drop down selections
A101: | | C101: TIPS | F101: \ Options for drop down selections
A102: ↓ | C102: OTHER | F102: \ Options for drop down selections
A104: DOCUMENT TYPES \ [ M_DOCTYPES ] \ memory variable list begins with blank line (C106) and continues until "Other" (C115)
A106: ↑
A107: M_DOCTYPES | C107: Awards Letter
A108: | | C108: Bank Statement
A109: | | C109: Earnings Statement
A110: | | C110: IRS Form 1099
A111: | | C111: Pay Statement
A112: | | C112: Tax Returns
A113: | | C113: VA Cert of Eligibility
A114: | | C114: W2
A115: ↓ | C115: Other
A117: BORROWER'S PAYSTUB
A119: VLOOKUP
A120: 1 | B120: 2 | C120: 3 | D120: 4 | E120: 5
A121: Search | B121: Pay Periods | C121: Hours | D121: Term | E121: Message
A122: =$C$54 -> Annually (1) | B122: =$E$49 -> 1 | C122: =$F$49 -> 2080 | D122: =$G$49 -> annually | E122: =IF(D135=0,"N/A",CONCATENATE("Working full-time at current rate of pay (",DOLLAR(D204,0)," annually), borrower's YTD earnings would need to reflect ",DOLLAR(D231,0)," as the total amount of base earnings from ",MONTH(C143),"/",DAY(C143),"/",YEAR(C143)," to ",MONTH(D143),"/",DAY(D143),"/",YEAR(D143)," (excluding bonus, commissions, differential, incentive, overtime, etc.).")) -> #REF!
A123: =$C$51 -> Bi-Weekly (26) | B123: =$E$50 -> 26 | C123: =$F$50 -> 80 | D123: =$G$50 -> bi-weekly | E123: =IF(D135=0,"N/A",CONCATENATE("Working full-time at current rate of pay (",DOLLAR(D204,0)," bi-weekly), borrower's YTD earnings would need to reflect ",DOLLAR(D231,0)," as the total amount of base earnings from ",MONTH(C143),"/",DAY(C143),"/",YEAR(C143)," to ",MONTH(D143),"/",DAY(D143),"/",YEAR(D143)," (excluding bonus, commissions, differential, incentive, overtime, etc.).")) -> #REF!
A124: =$C$49 -> Hourly (H) | B124: =$E$51 -> 2080 | C124: =$F$51 -> 1 | D124: =$G$51 -> hourly | E124: =IF(D135=0,"N/A",CONCATENATE("Working full-time at current rate of pay (",DOLLAR(D204,2)," hourly), borrower's YTD earnings would need to reflect ",DOLLAR(D231,0)," as the total amount of base earnings from ",MONTH(C143),"/",DAY(C143),"/",YEAR(C143)," to ",MONTH(D143),"/",DAY(D143),"/",YEAR(D143)," (excluding bonus, commissions, differential, incentive, overtime, etc.).")) -> #REF!
A125: =$C$53 -> Monthly (12) | B125: =$E$52 -> 12 | C125: =$F$52 -> 173.33333 | D125: =$G$52 -> monthly | E125: =IF(D135=0,"N/A",CONCATENATE("Working full-time at current rate of pay (",DOLLAR(D204,0)," monthly), borrower's YTD earnings would need to reflect ",DOLLAR(D231,0)," as the total amount of base earnings from ",MONTH(C143),"/",DAY(C143),"/",YEAR(C143)," to ",MONTH(D143),"/",DAY(D143),"/",YEAR(D143)," (excluding bonus, commissions, differential, incentive, overtime, etc.).")) -> #REF!
A126: =$C$55 -> Part-Time | B126: =$E$53 -> 0 | C126: =$F$53 -> 0 | D126: =$G$53 -> part-time | E126: =IF(D135=0,"N/A",CONCATENATE("Working Part-Time at averaged monthly pay, borrower's YTD earnings would need to reflect approximately ",DOLLAR(D231,0)," as the total amount of base earnings from ",MONTH(C143),"/",DAY(C143),"/",YEAR(C143)," to ",MONTH(D143),"/",DAY(D143),"/",YEAR(D143)," (excluding bonus, commissions, differential, incentive, overtime, etc.).")) -> #REF!
A127: =$C$56 -> Seasonal | B127: =$E$54 -> 0 | C127: =$F$54 -> 0 | D127: =$G$54 -> seasonal | E127: =IF(D135=0,"N/A",CONCATENATE("Working Seasonal at averaged monthly pay, borrower's YTD earnings would need to reflect approximately ",DOLLAR(D231,0)," as the total amount of base earnings from ",MONTH(C143),"/",DAY(C143),"/",YEAR(C143)," to ",MONTH(D143),"/",DAY(D143),"/",YEAR(D143)," (excluding bonus, commissions, differential, incentive, overtime, etc.).")) -> #REF!
A128: =$C$52 -> Semi-Monthly (24) | B128: =$E$55 -> 24 | C128: =$F$55 -> 86.666667 | D128: =$G$55 -> semi-monthly | E128: =IF(D135=0,"N/A",CONCATENATE("Working full-time at current rate of pay (",DOLLAR(D204,2)," semi-monthly), borrower's YTD earnings would need to reflect ",DOLLAR(D231,0)," as the total amount of base earnings from ",MONTH(C143),"/",DAY(C143),"/",YEAR(C143)," to ",MONTH(D143),"/",DAY(D143),"/",YEAR(D143)," (excluding bonus, commissions, differential, incentive, overtime, etc.).")) -> #REF!
A129: =$C$57 -> Varies / Averaged | B129: =$E$56 -> 0 | C129: =$F$56 -> 0 | D129: =$G$56 -> varies | E129: =IF(D135=0,"N/A",CONCATENATE("Based on calculated averaged monthly earnings, borrower's YTD earnings should reflect approximately ",DOLLAR(D231,0)," as the total amount of base income earned from ",MONTH(C143),"/",DAY(C143),"/",YEAR(C143)," to ",MONTH(D143),"/",DAY(D143),"/",YEAR(D143)," (excluding bonus, commissions, differential, incentive, overtime, etc.).")) -> #REF!
A130: =$C$50 -> Weekly (52) | B130: =$E$57 -> 52 | C130: =$F$57 -> 40 | D130: =$G$57 -> weekly | E130: =IF(D135=0,"N/A",CONCATENATE("Working full-time at current rate of pay (",DOLLAR(D204,2)," weekly), borrower's YTD earnings would need to reflect ",DOLLAR(D231,0)," as the total amount of base earnings from ",MONTH(C143),"/",DAY(C143),"/",YEAR(C143)," to ",MONTH(D143),"/",DAY(D143),"/",YEAR(D143)," (excluding bonus, commissions, differential, incentive, overtime, etc.).")) -> #REF!
A132: Document date | D132: =IF(#REF!="","",#REF!) -> #REF! | G132: / Date of document as entered by user in the box/field between document type and rate of pay
...

Sheet Res Inc Data
A2: Total Loan Amount | B2: =#REF! -> #REF!
A4: W2 - Gross Wages | B4: =#REF! -> #REF!
A5: W2 - Fed Income Tax | B5: =#REF! -> #REF!
A6: W2 - Social Security | B6: =B4*6.2% -> #REF!
A7: W2 - Medicare | B7: =B4*1.45% -> #REF!
A8: W2 - State Inc Tax | B8: =#REF! -> #REF!
A9: W2 - Other Inc Tax | B9: =#REF! -> #REF!
A10: W2 - Total Payroll Ded | B10: =SUM(B5:B9) -> #REF!
A11: W2 - Net Income | B11: =B4-B10 -> #REF!
A13: W2 - Gross Wages | B13: =#REF! -> #REF!
A14: W2 - Fed Income Tax | B14: =#REF! -> #REF!
A15: S/E - Social Security | B15: =B13*12.4% -> #REF!
A16: S/E - Medicare | B16: =B13*2.9% -> #REF!
A17: W2 - State Inc Tax | B17: =#REF! -> #REF!
A18: W2 - Other Inc Tax | B18: =#REF! -> #REF!
A19: S/E - Total Payroll Ded | B19: =SUM(B14:B18) -> #REF!
A20: S/E - Net Income | B20: =B13-B19 -> #REF!
A22: N/T - Gross Wages | B22: =#REF! -> #REF!
A23: N/T - Grossed Up Amt | B23: =#REF! -> #REF!
A24: N/T - Grand Total | B24: =SUM(B22:B23) -> #REF!
A26: PITIA | B26: =#REF! -> #REF!
A27: All Other Payments | B27: =#REF! -> #REF!
A28: Subj Prop Sq Ft | B28: =#REF! -> #REF!
A29: Housing Maintenance | B29: =B28*0.14 -> #REF!
A30: Total All Debts | B30: =B26+B27+B29 -> #REF!
A32: Grand Total Net Inc | B32: =(B11+B20+B22)-B30 -> #REF!
A33: Grand Total All Debt | B33: =#REF! -> #REF!
A35: Active Duty Selection | B35: Select for Veteran Borrowers
B36: Active Duty
B37: Separated from Service
A39: Active Duty Selected | B39: 1
A40: State Selected | B40: 1
A41: State Selected | B41: =VLOOKUP(B40,A67:B118,2) -> ALABAMA
A42: Family Size | B42: =FAMILYSIZE -> #REF!
A43: Active Duty | B43: =IF(B39=2,TRUE(),FALSE()) -> FALSE
A44: Residual Proposed | B44: =IF(OR(FAMILYSIZE="",FAMILYSIZE=0),0,IF(B2>=80000,VLOOKUP(STATESELECTED,D67:N118,FAMILYSIZE+1),IF(B2<80000,VLOOKUP(STATESELECTED,D129:N180,FAMILYSIZE+1),0))) -> #REF!
A45: Residual Required | B45: =IF(B43=TRUE(),B44*95%,B44) -> #REF!
A46: Residual Actual | B46: =B32-B33 -> #REF!
A47: Residual Difference ($) | B47: =RESIDUALACTUAL-RESIDUALREQUIRED -> #REF!
A48: Residual Difference (%) | B48: =IF(B46=0,0,ROUNDDOWN(B47/B44,0)) -> #REF!
A51: Message Line 1 | B51: =IF(OR(FAMILYSIZE="",RESIDUALACTUAL=0),"",CONCATENATE(" State of",STATESELECTED," and Family Size of ",FAMILYSIZE,)) -> #REF!
A52: Message Line 2 | B52: =IF(RESIDUALACTUAL=0,"",CONCATENATE("Actual Residual Income = ",DOLLAR(RESIDUALACTUAL,2))) -> #REF!
A53: Message Line 3 | B53: =IF(RESIDUALACTUAL=0,"",CONCATENATE("Actual Residual Income = ",DOLLAR(RESIDUALACTUAL,2))) -> #REF!
A54: Message Line 4 | B54: =IF(RESIDUALDIFF=0,"",IF(RESIDUALDIFF>0,CONCATENATE("Actual Residual Income EXCEEDS Guidelines by an additional ",ROUNDDOWN(RESIDUALDIFF*100,0),"%"),IF(RESIDUALDIFF<0,CONCATENATE("Actual Residual Income is INSUFFICIENT and DOES NOT meet minimum requirements.")))) -> #REF!
A58: VA Residual Income Data for Loan Amounts => $80,000
B60: Area | C60: State Abbr | D60: Area | E60: 1 | F60: 2 | G60: 3 | H60: 4 | I60: 5 | J60: 6 | K60: 7 | L60: 8 | M60: 9 | N60: 10
B61: NORTHEAST | D61: NORTHEAST | E61: 450 | F61: 755 | G61: 909 | H61: 1025 | I61: 1062 | J61: 1142 | K61: 1222 | L61: 1302 | M61: 1382 | N61: 1462
B62: MIDWEST | D62: MIDWEST | E62: 441 | F62: 738 | G62: 889 | H62: 1003 | I62: 1039 | J62: 1119 | K62: 1199 | L62: 1279 | M62: 1359 | N62: 1439
B63: SOUTH | D63: SOUTH | E63: 441 | F63: 738 | G63: 889 | H63: 1003 | I63: 1039 | J63: 1119 | K63: 1199 | L63: 1279 | M63: 1359 | N63: 1439
B64: WEST | D64: WEST | E64: 491 | F64: 823 | G64: 990 | H64: 1117 | I64: 1158 | J64: 1238 | K64: 1318 | L64: 1398 | M64: 1478 | N64: 1558
B66: State | C66: State Abbr | D66: State | E66: 1 | F66: 2 | G66: 3 | H66: 4 | I66: 5 | J66: 6 | K66: 7 | L66: 8 | M66: 9 | N66: 10 | O66: Region
A67: 1 | B67: ALABAMA | C67: AL | D67: ALABAMA | E67: =E$63 -> 441 | F67: =F$63 -> 738 | G67: =G$63 -> 889 | H67: =H$63 -> 1003 | I67: =I$63 -> 1039 | J67: =J$63 -> 1119 | K67: =K$63 -> 1199 | L67: =L$63 -> 1279 | ... N67: =N$63 -> 1439 | O67: S
A68: 2 | B68: ALASKA | C68: AK | D68: ALASKA | E68: =E$64 -> 491 | F68: =F$64 -> 823 | G68: =G$64 -> 990 | H68: =H$64 -> 1117 | I68: =I$64 -> 1158 | J68: =J$64 -> 1238 | K68: =K$64 -> 1318 | L68: =L$64 -> 1398 | ... N68: =N$64 -> 1558 | O68: W
A69: 3 | B69: ARIZONA | C69: AZ | D69: ARIZONA | E69: =E$64 -> 491 | F69: =F$64 -> 823 | G69: =G$64 -> 990 | H69: =H$64 -> 1117 | I69: =I$64 -> 1158 | J69: =J$64 -> 1238 | K69: =K$64 -> 1318 | L69: =L$64 -> 1398 | ... N69: =N$64 -> 1558 | O69: W
A70: 4 | B70: ARKANSAS | C70: AR | D70: ARKANSAS | E70: =E$63 -> 441 | F70: =F$63 -> 738 | G70: =G$63 -> 889 | H70: =H$63 -> 1003 | I70: =I$63 -> 1039 | J70: =J$63 -> 1119 | K70: =K$63 -> 1199 | L70: =L$63 -> 1279 | ... N70: =N$63 -> 1439 | O70: S
A71: 5 | B71: CALIFORNIA | C71: CA | D71: CALIFORNIA | E71: =E$64 -> 491 | F71: =F$64 -> 823 | G71: =G$64 -> 990 | H71: =H$64 -> 1117 | I71: =I$64 -> 1158 | J71: =J$64 -> 1238 | K71: =K$64 -> 1318 | L71: =L$64 -> 1398 | ... N71: =N$64 -> 1558 | O71: W
A72: 6 | B72: COLORADO | C72: CO | D72: COLORADO | E72: =E$64 -> 491 | F72: =F$64 -> 823 | G72: =G$64 -> 990 | H72: =H$64 -> 1117 | I72: =I$64 -> 1158 | J72: =J$64 -> 1238 | K72: =K$64 -> 1318 | L72: =L$64 -> 1398 | ... N72: =N$64 -> 1558 | O72: W
A73: 7 | B73: CONNECTICUT | C73: CT | D73: CONNECTICUT | E73: =E$61 -> 450 | F73: =F$61 -> 755 | G73: =G$61 -> 909 | H73: =H$61 -> 1025 | I73: =I$61 -> 1062 | J73: =J$61 -> 1142 | K73: =K$61 -> 1222 | L73: =L$61 -> 1302 | ... N73: =N$61 -> 1462 | O73: NE
A74: 8 | B74: DELAWARE | C74: DE | D74: DELAWARE | E74: =E$63 -> 441 | F74: =F$63 -> 738 | G74: =G$63 -> 889 | H74: =H$63 -> 1003 | I74: =I$63 -> 1039 | J74: =J$63 -> 1119 | K74: =K$63 -> 1199 | L74: =L$63 -> 1279 | ... N74: =N$63 -> 1439 | O74: S
A75: 9 | B75: DISTRICT OF COLUMBIA | C75: DC | D75: DISTRICT OF COLUMBIA | E75: =E$63 -> 441 | F75: =F$63 -> 738 | G75: =G$63 -> 889 | H75: =H$63 -> 1003 | I75: =I$63 -> 1039 | J75: =J$63 -> 1119 | K75: =K$63 -> 1199 | L75: =L$63 -> 1279 | ... N75: =N$63 -> 1439 | O75: S
A76: 10 | B76: FLORIDA | C76: FL | D76: FLORIDA | E76: =E$63 -> 441 | F76: =F$63 -> 738 | G76: =G$63 -> 889 | H76: =H$63 -> 1003 | I76: =I$63 -> 1039 | J76: =J$63 -> 1119 | K76: =K$63 -> 1199 | L76: =L$63 -> 1279 | ... N76: =N$63 -> 1439 | O76: S
A77: 11 | B77: GEORGIA | C77: GA | D77: GEORGIA | E77: =E$63 -> 441 | F77: =F$63 -> 738 | G77: =G$63 -> 889 | H77: =H$63 -> 1003 | I77: =I$63 -> 1039 | J77: =J$63 -> 1119 | K77: =K$63 -> 1199 | L77: =L$63 -> 1279 | ... N77: =N$63 -> 1439 | O77: S
A78: 12 | B78: HAWAII | C78: HI | D78: HAWAII | E78: =E$64 -> 491 | F78: =F$64 -> 823 | G78: =G$64 -> 990 | H78: =H$64 -> 1117 | I78: =I$64 -> 1158 | J78: =J$64 -> 1238 | K78: =K$64 -> 1318 | L78: =L$64 -> 1398 | ... N78: =N$64 -> 1558 | O78: W
A79: 13 | B79: IDAHO | C79: ID | D79: IDAHO | E79: =E$64 -> 491 | F79: =F$64 -> 823 | G79: =G$64 -> 990 | H79: =H$64 -> 1117 | I79: =I$64 -> 1158 | J79: =J$64 -> 1238 | K79: =K$64 -> 1318 | L79: =L$64 -> 1398 | ... N79: =N$64 -> 1558 | O79: W
A80: 14 | B80: ILLINOIS | C80: IL | D80: ILLINOIS | E80: =E$62 -> 441 | F80: =F$62 -> 738 | G80: =G$62 -> 889 | H80: =H$62 -> 1003 | I80: =I$62 -> 1039 | J80: =J$62 -> 1119 | K80: =K$62 -> 1199 | L80: =L$62 -> 1279 | ... N80: =N$62 -> 1439 | O80: MW
A81: 15 | B81: INDIANA | C81: IN | D81: INDIANA | E81: =E$62 -> 441 | F81: =F$62 -> 738 | G81: =G$62 -> 889 | H81: =H$62 -> 1003 | I81: =I$62 -> 1039 | J81: =J$62 -> 1119 | K81: =K$62 -> 1199 | L81: =L$62 -> 1279 | ... N81: =N$62 -> 1439 | O81: MW
A82: 16 | B82: IOWA | C82: IA | D82: IOWA | E82: =E$62 -> 441 | F82: =F$62 -> 738 | G82: =G$62 -> 889 | H82: =H$62 -> 1003 | I82: =I$62 -> 1039 | J82: =J$62 -> 1119 | K82: =K$62 -> 1199 | L82: =L$62 -> 1279 | ... N82: =N$62 -> 1439 | O82: MW
A83: 17 | B83: KANSAS | C83: KS | D83: KANSAS | E83: =E$62 -> 441 | F83: =F$62 -> 738 | G83: =G$62 -> 889 | H83: =H$62 -> 1003 | I83: =I$62 -> 1039 | J83: =J$62 -> 1119 | K83: =K$62 -> 1199 | L83: =L$62 -> 1279 | ... N83: =N$62 -> 1439 | O83: MW
A84: 18 | B84: KENTUCKY | C84: KY | D84: KENTUCKY | E84: =E$63 -> 441 | F84: =F$63 -> 738 | G84: =G$63 -> 889 | H84: =H$63 -> 1003 | I84: =I$63 -> 1039 | J84: =J$63 -> 1119 | K84: =K$63 -> 1199 | L84: =L$63 -> 1279 | ... N84: =N$63 -> 1439 | O84: S
A85: 19 | B85: LOUISIANA | C85: LA | D85: LOUISIANA | E85: =E$63 -> 441 | F85: =F$63 -> 738 | G85: =G$63 -> 889 | H85: =H$63 -> 1003 | I85: =I$63 -> 1039 | J85: =J$63 -> 1119 | K85: =K$63 -> 1199 | L85: =L$63 -> 1279 | ... N85: =N$63 -> 1439 | O85: S
A86: 20 | B86: MAINE | C86: ME | D86: MAINE | E86: =E$61 -> 450 | F86: =F$61 -> 755 | G86: =G$61 -> 909 | H86: =H$61 -> 1025 | I86: =I$61 -> 1062 | J86: =J$61 -> 1142 | K86: =K$61 -> 1222 | L86: =L$61 -> 1302 | ... N86: =N$61 -> 1462 | O86: NE
A87: 21 | B87: MARYLAND | C87: MD | D87: MARYLAND | E87: =E$63 -> 441 | F87: =F$63 -> 738 | G87: =G$63 -> 889 | H87: =H$63 -> 1003 | I87: =I$63 -> 1039 | J87: =J$63 -> 1119 | K87: =K$63 -> 1199 | L87: =L$63 -> 1279 | ... N87: =N$63 -> 1439 | O87: S
A88: 22 | B88: MASSACHUSETTS | C88: MA | D88: MASSACHUSETTS | E88: =E$61 -> 450 | F88: =F$61 -> 755 | G88: =G$61 -> 909 | H88: =H$61 -> 1025 | I88: =I$61 -> 1062 | J88: =J$61 -> 1142 | K88: =K$61 -> 1222 | L88: =L$61 -> 1302 | ... N88: =N$61 -> 1462 | O88: NE
A89: 23 | B89: MICHIGAN | C89: MI | D89: MICHIGAN | E89: =E$62 -> 441 | F89: =F$62 -> 738 | G89: =G$62 -> 889 | H89: =H$62 -> 1003 | I89: =I$62 -> 1039 | J89: =J$62 -> 1119 | K89: =K$62 -> 1199 | L89: =L$62 -> 1279 | ... N89: =N$62 -> 1439 | O89: MW
A90: 24 | B90: MINNESOTA | C90: MN | D90: MINNESOTA | E90: =E$62 -> 441 | F90: =F$62 -> 738 | G90: =G$62 -> 889 | H90: =H$62 -> 1003 | I90: =I$62 -> 1039 | J90: =J$62 -> 1119 | K90: =K$62 -> 1199 | L90: =L$62 -> 1279 | ... N90: =N$62 -> 1439 | O90: MW
A91: 25 | B91: MISSISSIPPI | C91: MS | D91: MISSISSIPPI | E91: =E$63 -> 441 | F91: =F$63 -> 738 | G91: =G$63 -> 889 | H91: =H$63 -> 1003 | I91: =I$63 -> 1039 | J91: =J$63 -> 1119 | K91: =K$63 -> 1199 | L91: =L$63 -> 1279 | ... N91: =N$63 -> 1439 | O91: S
A92: 26 | B92: MISSOURI | C92: MO | D92: MISSOURI | E92: =E$62 -> 441 | F92: =F$62 -> 738 | G92: =G$62 -> 889 | H92: =H$62 -> 1003 | I92: =I$62 -> 1039 | J92: =J$62 -> 1119 | K92: =K$62 -> 1199 | L92: =L$62 -> 1279 | ... N92: =N$62 -> 1439 | O92: MW
A93: 27 | B93: MONTANA | C93: MT | D93: MONTANA | E93: =E$64 -> 491 | F93: =F$64 -> 823 | G93: =G$64 -> 990 | H93: =H$64 -> 1117 | I93: =I$64 -> 1158 | J93: =J$64 -> 1238 | K93: =K$64 -> 1318 | L93: =L$64 -> 1398 | ... N93: =N$64 -> 1558 | O93: W
A94: 28 | B94: NEBRASKA | C94: NE | D94: NEBRASKA | E94: =E$62 -> 441 | F94: =F$62 -> 738 | G94: =G$62 -> 889 | H94: =H$62 -> 1003 | I94: =I$62 -> 1039 | J94: =J$62 -> 1119 | K94: =K$62 -> 1199 | L94: =L$62 -> 1279 | ... N94: =N$62 -> 1439 | O94: MW
A95: 29 | B95: NEVADA | C95: NV | D95: NEVADA | E95: =E$64 -> 491 | F95: =F$64 -> 823 | G95: =G$64 -> 990 | H95: =H$64 -> 1117 | I95: =I$64 -> 1158 | J95: =J$64 -> 1238 | K95: =K$64 -> 1318 | L95: =L$64 -> 1398 | ... N95: =N$64 -> 1558 | O95: W
A96: 30 | B96: NEW HAMPSHIRE | C96: NH | D96: NEW HAMPSHIRE | E96: =E$61 -> 450 | F96: =F$61 -> 755 | G96: =G$61 -> 909 | H96: =H$61 -> 1025 | I96: =I$61 -> 1062 | J96: =J$61 -> 1142 | K96: =K$61 -> 1222 | L96: =L$61 -> 1302 | ... N96: =N$61 -> 1462 | O96: NE
A97: 31 | B97: NEW JERSEY | C97: NJ | D97: NEW JERSEY | E97: =E$61 -> 450 | F97: =F$61 -> 755 | G97: =G$61 -> 909 | H97: =H$61 -> 1025 | I97: =I$61 -> 1062 | J97: =J$61 -> 1142 | K97: =K$61 -> 1222 | L97: =L$61 -> 1302 | ... N97: =N$61 -> 1462 | O97: NE
A98: 32 | B98: NEW MEXICO | C98: NM | D98: NEW MEXICO | E98: =E$64 -> 491 | F98: =F$64 -> 823 | G98: =G$64 -> 990 | H98: =H$64 -> 1117 | I98: =I$64 -> 1158 | J98: =J$64 -> 1238 | K98: =K$64 -> 1318 | L98: =L$64 -> 1398 | ... N98: =N$64 -> 1558 | O98: W
A99: 33 | B99: NEW YORK | C99: NY | D99: NEW YORK | E99: =E$61 -> 450 | F99: =F$61 -> 755 | G99: =G$61 -> 909 | H99: =H$61 -> 1025 | I99: =I$61 -> 1062 | J99: =J$61 -> 1142 | K99: =K$61 -> 1222 | L99: =L$61 -> 1302 | ... N99: =N$61 -> 1462 | O99: NE
A100: 34 | B100: NORTH CAROLINA | C100: NC | D100: NORTH CAROLINA | E100: =E$63 -> 441 | F100: =F$63 -> 738 | G100: =G$63 -> 889 | H100: =H$63 -> 1003 | I100: =I$63 -> 1039 | J100: =J$63 -> 1119 | K100: =K$63 -> 1199 | L100: =L$63 -> 1279 | ... N100: =N$63 -> 1439 | O100: S
A101: 35 | B101: NORTH DAKOTA | C101: ND | D101: NORTH DAKOTA | E101: =E$62 -> 441 | F101: =F$62 -> 738 | G101: =G$62 -> 889 | H101: =H$62 -> 1003 | I101: =I$62 -> 1039 | J101: =J$62 -> 1119 | K101: =K$62 -> 1199 | L101: =L$62 -> 1279 | ... N101: =N$62 -> 1439 | O101: MW
A102: 36 | B102: OHIO | C102: OH | D102: OHIO | E102: =E$62 -> 441 | F102: =F$62 -> 738 | G102: =G$62 -> 889 | H102: =H$62 -> 1003 | I102: =I$62 -> 1039 | J102: =J$62 -> 1119 | K102: =K$62 -> 1199 | L102: =L$62 -> 1279 | ... N102: =N$62 -> 1439 | O102: MW
A103: 37 | B103: OKLAHOMA | C103: OK | D103: OKLAHOMA | E103: =E$63 -> 441 | F103: =F$63 -> 738 | G103: =G$63 -> 889 | H103: =H$63 -> 1003 | I103: =I$63 -> 1039 | J103: =J$63 -> 1119 | K103: =K$63 -> 1199 | L103: =L$63 -> 1279 | ... N103: =N$63 -> 1439 | O103: S
A104: 38 | B104: OREGON | C104: OR | D104: OREGON | E104: =E$64 -> 491 | F104: =F$64 -> 823 | G104: =G$64 -> 990 | H104: =H$64 -> 1117 | I104: =I$64 -> 1158 | J104: =J$64 -> 1238 | K104: =K$64 -> 1318 | L104: =L$64 -> 1398 | ... N104: =N$64 -> 1558 | O104: W
A105: 39 | B105: PENNSYLVANIA | C105: PA | D105: PENNSYLVANIA | E105: =E$61 -> 450 | F105: =F$61 -> 755 | G105: =G$61 -> 909 | H105: =H$61 -> 1025 | I105: =I$61 -> 1062 | J105: =J$61 -> 1142 | K105: =K$61 -> 1222 | L105: =L$61 -> 1302 | ... N105: =N$61 -> 1462 | O105: NE
A106: 40 | B106: PUERTO RICO | C106: PR | D106: PUERTO RICO | E106: =E$63 -> 441 | F106: =F$63 -> 738 | G106: =G$63 -> 889 | H106: =H$63 -> 1003 | I106: =I$63 -> 1039 | J106: =J$63 -> 1119 | K106: =K$63 -> 1199 | L106: =L$63 -> 1279 | ... N106: =N$63 -> 1439 | O106: S
A107: 41 | B107: RHODE ISLAND | C107: RI | D107: RHODE ISLAND | E107: =E$61 -> 450 | F107: =F$61 -> 755 | G107: =G$61 -> 909 | H107: =H$61 -> 1025 | I107: =I$61 -> 1062 | J107: =J$61 -> 1142 | K107: =K$61 -> 1222 | L107: =L$61 -> 1302 | ... N107: =N$61 -> 1462 | O107: NE
A108: 42 | B108: SOUTH CAROLINA | C108: SC | D108: SOUTH CAROLINA | E108: =E$63 -> 441 | F108: =F$63 -> 738 | G108: =G$63 -> 889 | H108: =H$63 -> 1003 | I108: =I$63 -> 1039 | J108: =J$63 -> 1119 | K108: =K$63 -> 1199 | L108: =L$63 -> 1279 | ... N108: =N$63 -> 1439 | O108: S
A109: 43 | B109: SOUTH DAKOTA | C109: SD | D109: SOUTH DAKOTA | E109: =E$62 -> 441 | F109: =F$62 -> 738 | G109: =G$62 -> 889 | H109: =H$62 -> 1003 | I109: =I$62 -> 1039 | J109: =J$62 -> 1119 | K109: =K$62 -> 1199 | L109: =L$62 -> 1279 | ... N109: =N$62 -> 1439 | O109: MW
A110: 44 | B110: TENNESSEE | C110: TN | D110: TENNESSEE | E110: =E$63 -> 441 | F110: =F$63 -> 738 | G110: =G$63 -> 889 | H110: =H$63 -> 1003 | I110: =I$63 -> 1039 | J110: =J$63 -> 1119 | K110: =K$63 -> 1199 | L110: =L$63 -> 1279 | ... N110: =N$63 -> 1439 | O110: S
A111: 45 | B111: TEXAS | C111: TX | D111: TEXAS | E111: =E$63 -> 441 | F111: =F$63 -> 738 | G111: =G$63 -> 889 | H111: =H$63 -> 1003 | I111: =I$63 -> 1039 | J111: =J$63 -> 1119 | K111: =K$63 -> 1199 | L111: =L$63 -> 1279 | ... N111: =N$63 -> 1439 | O111: S
A112: 46 | B112: UTAH | C112: UT | D112: UTAH | E112: =E$64 -> 491 | F112: =F$64 -> 823 | G112: =G$64 -> 990 | H112: =H$64 -> 1117 | I112: =I$64 -> 1158 | J112: =J$64 -> 1238 | K112: =K$64 -> 1318 | L112: =L$64 -> 1398 | ... N112: =N$64 -> 1558 | O112: W
A113: 47 | B113: VERMONT | C113: VT | D113: VERMONT | E113: =E$61 -> 450 | F113: =F$61 -> 755 | G113: =G$61 -> 909 | H113: =H$61 -> 1025 | I113: =I$61 -> 1062 | J113: =J$61 -> 1142 | K113: =K$61 -> 1222 | L113: =L$61 -> 1302 | ... N113: =N$61 -> 1462 | O113: NE
A114: 48 | B114: VIRGINIA | C114: VA | D114: VIRGINIA | E114: =E$63 -> 441 | F114: =F$63 -> 738 | G114: =G$63 -> 889 | H114: =H$63 -> 1003 | I114: =I$63 -> 1039 | J114: =J$63 -> 1119 | K114: =K$63 -> 1199 | L114: =L$63 -> 1279 | ... N114: =N$63 -> 1439 | O114: S
A115: 49 | B115: WASHINGTON | C115: WA | D115: WASHINGTON | E115: =E$64 -> 491 | F115: =F$64 -> 823 | G115: =G$64 -> 990 | H115: =H$64 -> 1117 | I115: =I$64 -> 1158 | J115: =J$64 -> 1238 | K115: =K$64 -> 1318 | L115: =L$64 -> 1398 | ... N115: =N$64 -> 1558 | O115: W
...

Sheet MCC Credit
C3: MCC Credit Calculations
AQ6: =preparedby&" "&versionmsg -> #NAME?
C8: Borrower: | O8: =IF(#REF!="","",#REF!) -> #REF! | BQ8: Loan #: | CC8: =IF(#REF!="","",#REF!) -> #REF!
C12: Original Loan Amount | CH12: 0
C13: Interest Rate | CH13: 0
C14: Total Annual Interest | CH14: =CH12*CH13 -> 0
C15: Annual Tax Credit Percentage | CH15: 0.2
C16: Total Annual Tax Credit | CH16: =CH14*CH15 -> 0
C17: Total Annual Tax Credit Divided by 12 Months for Monthly Credit | CH17: 12
C18: Monthly Tax Credit Benefit for Qualifying Purposes | CH18: =CH16/CH17 -> 0
C22: AVERAGE EARNINGS (PAST 2 YEARS)
C23: Total Earnings (previous 2 years) | CH23: =SUM(AZ17:AZ18) -> 0
C24: Total Months Included in Total Earnings | CH24: =SUM(BQ17:BQ18) -> 0
C25: Average Total Monthly Earnings | CH25: =IF(CH24=0,"",CH23/CH24)
C27: Total Average Earnings for the past 2 years | CH27: =IF(CH25="","",IF(CH25>0,ROUNDDOWN(CH25,0),""))
C31: NOTES
C35: This worksheet is not intended to be legal or comprehensive financial advice. The user assumes any legal liability and responsibility
C36: for the accuracy, completeness, usefulness, effectiveness, reliability, information and/or results obtained from the use of this worksheet.
C37: It is the responsibility of the user to be knowledgeable of the text and data contained in the worksheet, to ensure the accuracy of any
C38: documentation used to complete the worksheet, and that contents are in accordance with product, investor and regulatory requirements.
